setup.py
distributions_pypi/Binomialdistribution.py
distributions_pypi/Gaussiandistribution.py
distributions_pypi/Generaldistribution.py
distributions_pypi/__init__.py
distributions_pypi.egg-info/PKG-INFO
distributions_pypi.egg-info/SOURCES.txt
distributions_pypi.egg-info/dependency_links.txt
distributions_pypi.egg-info/not-zip-safe
distributions_pypi.egg-info/top_level.txt