Metadata-Version: 1.0
Name: distributions-pypi
Version: 1.5
Summary: Gaussian and Binomial distributions
Home-page: UNKNOWN
Author: Myron Valenzuela
Author-email: myron@kupwise.com
License: UNKNOWN
Platform: UNKNOWN
